{"add":{"path":"category=Food%2520%2526%2520Beverage/part-00001-83954d95-edcb-488e-a436-2a59d7b50c19-c000.snappy.parquet","partitionValues":{"category":"Food & Beverage"},"size":293552,"modificationTime":1740282035602,"dataChange":true,"stats":"{\"numRecords\":14776,\"minValues\":{\"shopping_mall\":\"Cevahir AVM\",\"invoice_no\":\"I100031\",\"payment_method\":\"Cash\",\"invoice_date\":\"1/1/2021\",\"age\":18,\"quantity\":1,\"customer_id\":\"C100012\",\"price\":5.23,\"gender\":\"Female\"},\"maxValues\":{\"price\":26.15,\"invoice_date\":\"9/9/2022\",\"shopping_mall\":\"Zorlu Center\",\"age\":69,\"payment_method\":\"Debit Card\",\"invoice_no\":\"I999952\",\"gender\":\"Male\",\"quantity\":5,\"customer_id\":\"C999886\"},\"nullCount\":{\"price\":0,\"payment_method\":0,\"invoice_date\":0,\"customer_id\":0,\"gender\":0,\"quantity\":0,\"age\":0,\"shopping_mall\":0,\"invoice_no\":0}}","tags":null,"deletionVector":null,"baseRowId":null,"defaultRowCommitVersion":null,"clusteringProvider":null}}
{"add":{"path":"category=Clothing/part-00001-1b684eae-0f27-43e0-af84-39265d45eb95-c000.snappy.parquet","partitionValues":{"category":"Clothing"},"size":685203,"modificationTime":1740282035621,"dataChange":true,"stats":"{\"numRecords\":34487,\"minValues\":{\"customer_id\":\"C100004\",\"payment_method\":\"Cash\",\"invoice_no\":\"I100008\",\"age\":18,\"gender\":\"Female\",\"quantity\":1,\"invoice_date\":\"1/1/2021\",\"shopping_mall\":\"Cevahir AVM\",\"price\":300.08},\"maxValues\":{\"payment_method\":\"Debit Card\",\"age\":69,\"price\":1500.4,\"quantity\":5,\"invoice_date\":\"9/9/2022\",\"customer_id\":\"C999995\",\"shopping_mall\":\"Zorlu Center\",\"invoice_no\":\"I999959\",\"gender\":\"Male\"},\"nullCount\":{\"invoice_no\":0,\"price\":0,\"age\":0,\"customer_id\":0,\"quantity\":0,\"shopping_mall\":0,\"invoice_date\":0,\"gender\":0,\"payment_method\":0}}","tags":null,"deletionVector":null,"baseRowId":null,"defaultRowCommitVersion":null,"clusteringProvider":null}}
{"add":{"path":"category=Technology/part-00001-883c5673-2a0c-43fd-9d38-1ebc1e94b463-c000.snappy.parquet","partitionValues":{"category":"Technology"},"size":103151,"modificationTime":1740282035595,"dataChange":true,"stats":"{\"numRecords\":4996,\"minValues\":{\"quantity\":1,\"price\":1050.0,\"payment_method\":\"Cash\",\"gender\":\"Female\",\"customer_id\":\"C100139\",\"age\":18,\"shopping_mall\":\"Cevahir AVM\",\"invoice_no\":\"I100027\",\"invoice_date\":\"1/1/2021\"},\"maxValues\":{\"age\":69,\"invoice_date\":\"9/9/2022\",\"customer_id\":\"C999272\",\"invoice_no\":\"I999994\",\"gender\":\"Male\",\"quantity\":5,\"payment_method\":\"Debit Card\",\"price\":5250.0,\"shopping_mall\":\"Zorlu Center\"},\"nullCount\":{\"gender\":0,\"invoice_date\":0,\"customer_id\":0,\"age\":0,\"shopping_mall\":0,\"invoice_no\":0,\"payment_method\":0,\"quantity\":0,\"price\":0}}","tags":null,"deletionVector":null,"baseRowId":null,"defaultRowCommitVersion":null,"clusteringProvider":null}}
{"add":{"path":"category=Shoes/part-00001-813ca2a3-1b96-49e8-aaf3-c51430973e7a-c000.snappy.parquet","partitionValues":{"category":"Shoes"},"size":201797,"modificationTime":1740282035600,"dataChange":true,"stats":"{\"numRecords\":10034,\"minValues\":{\"invoice_no\":\"I100049\",\"payment_method\":\"Cash\",\"age\":18,\"gender\":\"Female\",\"invoice_date\":\"1/1/2021\",\"customer_id\":\"C100005\",\"price\":600.17,\"shopping_mall\":\"Cevahir AVM\",\"quantity\":1},\"maxValues\":{\"customer_id\":\"C999685\",\"gender\":\"Male\",\"invoice_date\":\"9/9/2022\",\"price\":3000.85,\"quantity\":5,\"invoice_no\":\"I999922\",\"age\":69,\"payment_method\":\"Debit Card\",\"shopping_mall\":\"Zorlu Center\"},\"nullCount\":{\"age\":0,\"customer_id\":0,\"invoice_no\":0,\"quantity\":0,\"gender\":0,\"payment_method\":0,\"shopping_mall\":0,\"price\":0,\"invoice_date\":0}}","tags":null,"deletionVector":null,"baseRowId":null,"defaultRowCommitVersion":null,"clusteringProvider":null}}
{"add":{"path":"category=Books/part-00001-c31a8451-066e-49c7-84e3-2e8ed0001dad-c000.snappy.parquet","partitionValues":{"category":"Books"},"size":102978,"modificationTime":1740282035607,"dataChange":true,"stats":"{\"numRecords\":4981,\"minValues\":{\"price\":15.15,\"shopping_mall\":\"Cevahir AVM\",\"invoice_no\":\"I100024\",\"customer_id\":\"C100028\",\"invoice_date\":\"1/1/2021\",\"quantity\":1,\"age\":18,\"payment_method\":\"Cash\",\"gender\":\"Female\"},\"maxValues\":{\"invoice_no\":\"I999769\",\"payment_method\":\"Debit Card\",\"invoice_date\":\"9/9/2022\",\"customer_id\":\"C999910\",\"age\":69,\"gender\":\"Male\",\"price\":75.75,\"shopping_mall\":\"Zorlu Center\",\"quantity\":5},\"nullCount\":{\"customer_id\":0,\"quantity\":0,\"shopping_mall\":0,\"invoice_no\":0,\"age\":0,\"payment_method\":0,\"invoice_date\":0,\"gender\":0,\"price\":0}}","tags":null,"deletionVector":null,"baseRowId":null,"defaultRowCommitVersion":null,"clusteringProvider":null}}
{"add":{"path":"category=Souvenir/part-00001-feff0d3e-2614-48d2-ab49-65a55ef629a1-c000.snappy.parquet","partitionValues":{"category":"Souvenir"},"size":103150,"modificationTime":1740282035591,"dataChange":true,"stats":"{\"numRecords\":4999,\"minValues\":{\"price\":11.73,\"payment_method\":\"Cash\",\"invoice_no\":\"I100059\",\"customer_id\":\"C100121\",\"shopping_mall\":\"Cevahir AVM\",\"quantity\":1,\"gender\":\"Female\",\"invoice_date\":\"1/1/2021\",\"age\":18},\"maxValues\":{\"gender\":\"Male\",\"shopping_mall\":\"Zorlu Center\",\"price\":58.65,\"invoice_no\":\"I999852\",\"quantity\":5,\"customer_id\":\"C999683\",\"age\":69,\"invoice_date\":\"9/9/2022\",\"payment_method\":\"Debit Card\"},\"nullCount\":{\"gender\":0,\"payment_method\":0,\"price\":0,\"invoice_date\":0,\"shopping_mall\":0,\"invoice_no\":0,\"age\":0,\"customer_id\":0,\"quantity\":0}}","tags":null,"deletionVector":null,"baseRowId":null,"defaultRowCommitVersion":null,"clusteringProvider":null}}
{"add":{"path":"category=Cosmetics/part-00001-2ee45df6-f124-4808-9f93-6ba134e9a79c-c000.snappy.parquet","partitionValues":{"category":"Cosmetics"},"size":299592,"modificationTime":1740282035602,"dataChange":true,"stats":"{\"numRecords\":15097,\"minValues\":{\"price\":40.66,\"invoice_date\":\"1/1/2021\",\"invoice_no\":\"I100014\",\"customer_id\":\"C100042\",\"quantity\":1,\"age\":18,\"gender\":\"Female\",\"shopping_mall\":\"Cevahir AVM\",\"payment_method\":\"Cash\"},\"maxValues\":{\"payment_method\":\"Debit Card\",\"invoice_date\":\"9/9/2022\",\"invoice_no\":\"I999344\",\"customer_id\":\"C999810\",\"gender\":\"Male\",\"age\":69,\"quantity\":5,\"price\":203.3,\"shopping_mall\":\"Zorlu Center\"},\"nullCount\":{\"payment_method\":0,\"age\":0,\"invoice_no\":0,\"quantity\":0,\"gender\":0,\"price\":0,\"customer_id\":0,\"shopping_mall\":0,\"invoice_date\":0}}","tags":null,"deletionVector":null,"baseRowId":null,"defaultRowCommitVersion":null,"clusteringProvider":null}}
{"add":{"path":"category=Toys/part-00001-d3e3efef-95d0-4ab3-ac81-635290edeeba-c000.snappy.parquet","partitionValues":{"category":"Toys"},"size":203121,"modificationTime":1740282035599,"dataChange":true,"stats":"{\"numRecords\":10087,\"minValues\":{\"gender\":\"Female\",\"invoice_date\":\"1/1/2021\",\"price\":35.84,\"shopping_mall\":\"Cevahir AVM\",\"age\":18,\"quantity\":1,\"customer_id\":\"C100006\",\"payment_method\":\"Cash\",\"invoice_no\":\"I100068\"},\"maxValues\":{\"invoice_no\":\"I999956\",\"shopping_mall\":\"Zorlu Center\",\"payment_method\":\"Debit Card\",\"gender\":\"Male\",\"price\":179.2,\"customer_id\":\"C999976\",\"invoice_date\":\"9/9/2022\",\"age\":69,\"quantity\":5},\"nullCount\":{\"age\":0,\"price\":0,\"gender\":0,\"payment_method\":0,\"customer_id\":0,\"invoice_no\":0,\"invoice_date\":0,\"quantity\":0,\"shopping_mall\":0}}","tags":null,"deletionVector":null,"baseRowId":null,"defaultRowCommitVersion":null,"clusteringProvider":null}}
{"metaData":{"id":"d1ca4c82-9ffa-4d95-b120-fcd6e91e6018","name":null,"description":null,"format":{"provider":"parquet","options":{}},"schemaString":"{\"type\":\"struct\",\"fields\":[{\"name\":\"invoice_no\",\"type\":\"string\",\"nullable\":true,\"metadata\":{}},{\"name\":\"customer_id\",\"type\":\"string\",\"nullable\":true,\"metadata\":{}},{\"name\":\"gender\",\"type\":\"string\",\"nullable\":true,\"metadata\":{}},{\"name\":\"age\",\"type\":\"long\",\"nullable\":true,\"metadata\":{}},{\"name\":\"quantity\",\"type\":\"long\",\"nullable\":true,\"metadata\":{}},{\"name\":\"price\",\"type\":\"double\",\"nullable\":true,\"metadata\":{}},{\"name\":\"payment_method\",\"type\":\"string\",\"nullable\":true,\"metadata\":{}},{\"name\":\"invoice_date\",\"type\":\"string\",\"nullable\":true,\"metadata\":{}},{\"name\":\"shopping_mall\",\"type\":\"string\",\"nullable\":true,\"metadata\":{}},{\"name\":\"category\",\"type\":\"string\",\"nullable\":true,\"metadata\":{}}]}","partitionColumns":["category"],"createdTime":1740282006453,"configuration":{}}}
{"remove":{"path":"category=Clothing/part-00001-b4b364aa-fca6-4e4d-a228-b2a06175de08-c000.snappy.parquet","dataChange":true,"deletionTimestamp":1740282035621,"extendedFileMetadata":true,"partitionValues":{"category":"Clothing"},"size":685203}}
{"remove":{"path":"category=Cosmetics/part-00001-0c648b3b-3b66-4dde-a9b9-80613c155582-c000.snappy.parquet","dataChange":true,"deletionTimestamp":1740282035621,"extendedFileMetadata":true,"partitionValues":{"category":"Cosmetics"},"size":299592}}
{"remove":{"path":"category=Technology/part-00001-42de6039-07d8-4601-acf6-0731f6d8b39a-c000.snappy.parquet","dataChange":true,"deletionTimestamp":1740282035621,"extendedFileMetadata":true,"partitionValues":{"category":"Technology"},"size":103151}}
{"remove":{"path":"category=Toys/part-00001-e6ff56af-30d1-4dd7-9c6e-54ebbe24d14d-c000.snappy.parquet","dataChange":true,"deletionTimestamp":1740282035621,"extendedFileMetadata":true,"partitionValues":{"category":"Toys"},"size":203121}}
{"remove":{"path":"category=Food%2520%2526%2520Beverage/part-00001-f4183718-af74-4005-9aa6-91040de9c60f-c000.snappy.parquet","dataChange":true,"deletionTimestamp":1740282035621,"extendedFileMetadata":true,"partitionValues":{"category":"Food & Beverage"},"size":293552}}
{"remove":{"path":"category=Shoes/part-00001-aa524579-7386-4871-aafb-4b191b31f801-c000.snappy.parquet","dataChange":true,"deletionTimestamp":1740282035621,"extendedFileMetadata":true,"partitionValues":{"category":"Shoes"},"size":201797}}
{"remove":{"path":"category=Souvenir/part-00001-b03bfb3b-1d90-4b4a-a67b-cf1d21afb329-c000.snappy.parquet","dataChange":true,"deletionTimestamp":1740282035621,"extendedFileMetadata":true,"partitionValues":{"category":"Souvenir"},"size":103150}}
{"remove":{"path":"category=Books/part-00001-37cf85b7-c95a-4888-97f9-b0368cfe1486-c000.snappy.parquet","dataChange":true,"deletionTimestamp":1740282035621,"extendedFileMetadata":true,"partitionValues":{"category":"Books"},"size":102978}}
{"commitInfo":{"timestamp":1740282035621,"operation":"WRITE","operationParameters":{"mode":"Overwrite","partitionBy":"[\"category\"]"},"operationMetrics":{"execution_time_ms":76,"num_added_files":8,"num_added_rows":99457,"num_partitions":1032,"num_removed_files":8},"clientVersion":"delta-rs.0.23.1"}}